Workbook

Sheet Бланка_Предложения
A1: ВЕРИГА СУПЕРМАРКЕТИ „БАКАЛИЯ“ — ЦЕНТРАЛЕН ТЪРГОВСКИ ОФИС
A2: СТАНДАРТИЗИРАНА БЛАНКА ЗА ОФЕРИРАНЕ НА АРТИКУЛИ ЗА ПРОМОЦИОНАЛНА БРОШУРА (2027 Г.)
A4: 📅 1. ПАРАМЕТРИ НА КАМПАНИЯТА | I4: 🏢 2. ДАННИ ЗА ПАРТНЬОРА / ДОСТАВЧИКА
A5: Целева Брошура (падащ списък): | D5: Брошура № 01 | I5: Фирма / Контрагент: | L5: Въведете фирма
A6: Период на промоцията в магазините: | D6: =VLOOKUP(D5, График_2027!$A$3:$I$27, 4, FALSE) | I6: Бранд / Търговска марка: | L6: Въведете бранд
A7: Период намалена доставна цена (ЗКП): | D7: =VLOOKUP(D5, График_2027!$A$3:$I$27, 6, FALSE) | I7: Лице за контакт: | L7: Име и фамилия
A8: Краен срок за връщане на бланката: | D8: =VLOOKUP(D5, График_2027!$A$3:$I$27, 7, FALSE) & " (до 17:00 ч.)" | I8: Телефон и Имейл за връзка: | L8: тел. / имейл
A10: ⚠️ ВАЖНО: 1) Промоционалната доставна цена (ЗКП) влиза в сила точно 7 дни преди старта на брошурата! 2) Попълвайте само жълтите полета. 3) Формулите за марж, отстъпки и статуси се смятат автоматично.
A11: БРОЙ ПРЕДЛОЖЕНИЯ | D11: СРЕДНА ТО НА ВХОДА | G11: СРЕДНО НАМАЛЕНИЕ ЗА КЛИЕНТА | J11: СРЕДЕН ПРОГНОЗЕН МАРЖ | N11: ОБЩ БРОЙ КАРЕТА / УЧАСТИЯ
A12: =COUNTA(D15:D49) | D12: =IFERROR(AVERAGE(I15:I49), 0) | G12: =IFERROR(AVERAGE(L15:L49), 0) | J12: =IFERROR(AVERAGE(M15:M49), 0) | N12: =SUM(P15:P49)
A14: № | B14: Код в Бакалия (Мистрал ID) | C14: Баркод (EAN-13) | D14: Наименование на артикула (по етикет в каре) | E14: Мярка / Грамаж | F14: Бранд / Производител | G14: Редовна Д.Ц. без ДДС (лв.) | H14: ПРОМО Д.Ц. без ДДС (лв.) | I14: Търговска отстъпка ТО % | J14: Редовна П.Ц. с ДДС (лв.) | K14: ПРОМО П.Ц. с ДДС (лв.) | L14: Клиентска отстъпка % | M14: Брутен марж за Бакалия % | N14: Статус на маржа | O14: Издание (Период) | P14: Брой карета | Q14: Специфика / Забележка за предпечата
A15: 1 | B15: 5075 | C15: 380000000001 | D15: Мляно месо 100% свинско | E15: кг. | F15: Собствено | G15: 3.07 | H15: 2.7 | I15: =IF(AND(ISNUMBER(G15),ISNUMBER(H15),G15>0),(G15-H15)/G15,"") | J15: 4.99 | K15: 3.99 | L15: =IF(AND(ISNUMBER(J15),ISNUMBER(K15),J15>0),(J15-K15)/J15,"") | M15: =IF(AND(ISNUMBER(K15),ISNUMBER(H15),K15>0),((K15/1.2)-H15)/(K15/1.2),"") | N15: =IF(M15="","",IF(M15>=0.22,"🟢 Отличен",IF(M15>=0.15,"🟡 За преглед","🔴 Нисък марж"))) | O15: Брошура 1 | P15: 1 | Q15: Корица / ТОП цена
A16: 2 | B16: 18974 | C16: 380000000002 | D16: Кет Джой пастет за котки | E16: 100гр. | F16: Кет Джой | G16: 0.39 | H16: 0.32 | I16: =IF(AND(ISNUMBER(G16),ISNUMBER(H16),G16>0),(G16-H16)/G16,"") | J16: 0.79 | K16: 0.49 | L16: =IF(AND(ISNUMBER(J16),ISNUMBER(K16),J16>0),(J16-K16)/J16,"") | M16: =IF(AND(ISNUMBER(K16),ISNUMBER(H16),K16>0),((K16/1.2)-H16)/(K16/1.2),"") | N16: =IF(M16="","",IF(M16>=0.22,"🟢 Отличен",IF(M16>=0.15,"🟡 За преглед","🔴 Нисък марж"))) | O16: Брошура 1 | P16: 1 | Q16: Различни вкусове
A17: 3 | B17: 15044 | C17: 380000000003 | D17: Airwick фреш матик пълнител | E17: 250мл. | F17: Аксон | G17: 5.36 | H17: 4.41 | I17: =IF(AND(ISNUMBER(G17),ISNUMBER(H17),G17>0),(G17-H17)/G17,"") | J17: 7.56 | K17: 4.99 | L17: =IF(AND(ISNUMBER(J17),ISNUMBER(K17),J17>0),(J17-K17)/J17,"") | M17: =IF(AND(ISNUMBER(K17),ISNUMBER(H17),K17>0),((K17/1.2)-H17)/(K17/1.2),"") | N17: =IF(M17="","",IF(M17>=0.22,"🟢 Отличен",IF(M17>=0.15,"🟡 За преглед","🔴 Нисък марж"))) | O17: Брошура 1 | P17: 1 | Q17: Асортимент аромати
A18: 4 | B18: 7524 | C18: 380000000004 | D18: Аспазия газирани напитки | E18: 2л. | F18: Аспазия 92 | G18: 0.67 | H18: 0.53 | I18: =IF(AND(ISNUMBER(G18),ISNUMBER(H18),G18>0),(G18-H18)/G18,"") | J18: 1.02 | K18: 0.65 | L18: =IF(AND(ISNUMBER(J18),ISNUMBER(K18),J18>0),(J18-K18)/J18,"") | M18: =IF(AND(ISNUMBER(K18),ISNUMBER(H18),K18>0),((K18/1.2)-H18)/(K18/1.2),"") | N18: =IF(M18="","",IF(M18>=0.22,"🟢 Отличен",IF(M18>=0.15,"🟡 За преглед","🔴 Нисък марж"))) | O18: Брошура 2 | P18: 1 | Q18: Портокал / Лимон
A19: 5 | B19: 5147 | C19: 380000000005 | D19: Здравец кисело мляко 2% | E19: 500гр. | F19: Бел Групс | G19: 0.72 | H19: 0.61 | I19: =IF(AND(ISNUMBER(G19),ISNUMBER(H19),G19>0),(G19-H19)/G19,"") | J19: 0.96 | K19: 0.79 | L19: =IF(AND(ISNUMBER(J19),ISNUMBER(K19),J19>0),(J19-K19)/J19,"") | M19: =IF(AND(ISNUMBER(K19),ISNUMBER(H19),K19>0),((K19/1.2)-H19)/(K19/1.2),"") | N19: =IF(M19="","",IF(M19>=0.22,"🟢 Отличен",IF(M19>=0.15,"🟡 За преглед","🔴 Нисък марж"))) | O19: Брошура 2 | P19: 1 | Q19: БДС стандарт
A20: 6 | I20: =IF(AND(ISNUMBER(G20),ISNUMBER(H20),G20>0),(G20-H20)/G20,"") | L20: =IF(AND(ISNUMBER(J20),ISNUMBER(K20),J20>0),(J20-K20)/J20,"") | M20: =IF(AND(ISNUMBER(K20),ISNUMBER(H20),K20>0),((K20/1.2)-H20)/(K20/1.2),"") | N20: =IF(M20="","",IF(M20>=0.22,"🟢 Отличен",IF(M20>=0.15,"🟡 За преглед","🔴 Нисък марж"))) | O20: Брошура 1 | P20: 1
A21: 7 | I21: =IF(AND(ISNUMBER(G21),ISNUMBER(H21),G21>0),(G21-H21)/G21,"") | L21: =IF(AND(ISNUMBER(J21),ISNUMBER(K21),J21>0),(J21-K21)/J21,"") | M21: =IF(AND(ISNUMBER(K21),ISNUMBER(H21),K21>0),((K21/1.2)-H21)/(K21/1.2),"") | N21: =IF(M21="","",IF(M21>=0.22,"🟢 Отличен",IF(M21>=0.15,"🟡 За преглед","🔴 Нисък марж"))) | O21: Брошура 1 | P21: 1
A22: 8 | I22: =IF(AND(ISNUMBER(G22),ISNUMBER(H22),G22>0),(G22-H22)/G22,"") | L22: =IF(AND(ISNUMBER(J22),ISNUMBER(K22),J22>0),(J22-K22)/J22,"") | M22: =IF(AND(ISNUMBER(K22),ISNUMBER(H22),K22>0),((K22/1.2)-H22)/(K22/1.2),"") | N22: =IF(M22="","",IF(M22>=0.22,"🟢 Отличен",IF(M22>=0.15,"🟡 За преглед","🔴 Нисък марж"))) | O22: Брошура 1 | P22: 1
A23: 9 | I23: =IF(AND(ISNUMBER(G23),ISNUMBER(H23),G23>0),(G23-H23)/G23,"") | L23: =IF(AND(ISNUMBER(J23),ISNUMBER(K23),J23>0),(J23-K23)/J23,"") | M23: =IF(AND(ISNUMBER(K23),ISNUMBER(H23),K23>0),((K23/1.2)-H23)/(K23/1.2),"") | N23: =IF(M23="","",IF(M23>=0.22,"🟢 Отличен",IF(M23>=0.15,"🟡 За преглед","🔴 Нисък марж"))) | O23: Брошура 1 | P23: 1
A24: 10 | I24: =IF(AND(ISNUMBER(G24),ISNUMBER(H24),G24>0),(G24-H24)/G24,"") | L24: =IF(AND(ISNUMBER(J24),ISNUMBER(K24),J24>0),(J24-K24)/J24,"") | M24: =IF(AND(ISNUMBER(K24),ISNUMBER(H24),K24>0),((K24/1.2)-H24)/(K24/1.2),"") | N24: =IF(M24="","",IF(M24>=0.22,"🟢 Отличен",IF(M24>=0.15,"🟡 За преглед","🔴 Нисък марж"))) | O24: Брошура 1 | P24: 1
A25: 11 | I25: =IF(AND(ISNUMBER(G25),ISNUMBER(H25),G25>0),(G25-H25)/G25,"") | L25: =IF(AND(ISNUMBER(J25),ISNUMBER(K25),J25>0),(J25-K25)/J25,"") | M25: =IF(AND(ISNUMBER(K25),ISNUMBER(H25),K25>0),((K25/1.2)-H25)/(K25/1.2),"") | N25: =IF(M25="","",IF(M25>=0.22,"🟢 Отличен",IF(M25>=0.15,"🟡 За преглед","🔴 Нисък марж"))) | O25: Брошура 1 | P25: 1
A26: 12 | I26: =IF(AND(ISNUMBER(G26),ISNUMBER(H26),G26>0),(G26-H26)/G26,"") | L26: =IF(AND(ISNUMBER(J26),ISNUMBER(K26),J26>0),(J26-K26)/J26,"") | M26: =IF(AND(ISNUMBER(K26),ISNUMBER(H26),K26>0),((K26/1.2)-H26)/(K26/1.2),"") | N26: =IF(M26="","",IF(M26>=0.22,"🟢 Отличен",IF(M26>=0.15,"🟡 За преглед","🔴 Нисък марж"))) | O26: Брошура 1 | P26: 1
A27: 13 | I27: =IF(AND(ISNUMBER(G27),ISNUMBER(H27),G27>0),(G27-H27)/G27,"") | L27: =IF(AND(ISNUMBER(J27),ISNUMBER(K27),J27>0),(J27-K27)/J27,"") | M27: =IF(AND(ISNUMBER(K27),ISNUMBER(H27),K27>0),((K27/1.2)-H27)/(K27/1.2),"") | N27: =IF(M27="","",IF(M27>=0.22,"🟢 Отличен",IF(M27>=0.15,"🟡 За преглед","🔴 Нисък марж"))) | O27: Брошура 1 | P27: 1
A28: 14 | I28: =IF(AND(ISNUMBER(G28),ISNUMBER(H28),G28>0),(G28-H28)/G28,"") | L28: =IF(AND(ISNUMBER(J28),ISNUMBER(K28),J28>0),(J28-K28)/J28,"") | M28: =IF(AND(ISNUMBER(K28),ISNUMBER(H28),K28>0),((K28/1.2)-H28)/(K28/1.2),"") | N28: =IF(M28="","",IF(M28>=0.22,"🟢 Отличен",IF(M28>=0.15,"🟡 За преглед","🔴 Нисък марж"))) | O28: Брошура 1 | P28: 1
A29: 15 | I29: =IF(AND(ISNUMBER(G29),ISNUMBER(H29),G29>0),(G29-H29)/G29,"") | L29: =IF(AND(ISNUMBER(J29),ISNUMBER(K29),J29>0),(J29-K29)/J29,"") | M29: =IF(AND(ISNUMBER(K29),ISNUMBER(H29),K29>0),((K29/1.2)-H29)/(K29/1.2),"") | N29: =IF(M29="","",IF(M29>=0.22,"🟢 Отличен",IF(M29>=0.15,"🟡 За преглед","🔴 Нисък марж"))) | O29: Брошура 1 | P29: 1
A30: 16 | I30: =IF(AND(ISNUMBER(G30),ISNUMBER(H30),G30>0),(G30-H30)/G30,"") | L30: =IF(AND(ISNUMBER(J30),ISNUMBER(K30),J30>0),(J30-K30)/J30,"") | M30: =IF(AND(ISNUMBER(K30),ISNUMBER(H30),K30>0),((K30/1.2)-H30)/(K30/1.2),"") | N30: =IF(M30="","",IF(M30>=0.22,"🟢 Отличен",IF(M30>=0.15,"🟡 За преглед","🔴 Нисък марж"))) | O30: Брошура 1 | P30: 1
A31: 17 | I31: =IF(AND(ISNUMBER(G31),ISNUMBER(H31),G31>0),(G31-H31)/G31,"") | L31: =IF(AND(ISNUMBER(J31),ISNUMBER(K31),J31>0),(J31-K31)/J31,"") | M31: =IF(AND(ISNUMBER(K31),ISNUMBER(H31),K31>0),((K31/1.2)-H31)/(K31/1.2),"") | N31: =IF(M31="","",IF(M31>=0.22,"🟢 Отличен",IF(M31>=0.15,"🟡 За преглед","🔴 Нисък марж"))) | O31: Брошура 1 | P31: 1
... A49: 35 | I49: =IF(AND(ISNUMBER(G49),ISNUMBER(H49),G49>0),(G49-H49)/G49,"") | L49: =IF(AND(ISNUMBER(J49),ISNUMBER(K49),J49>0),(J49-K49)/J49,"") | M49: =IF(AND(ISNUMBER(K49),ISNUMBER(H49),K49>0),((K49/1.2)-H49)/(K49/1.2),"") | N49: =IF(M49="","",IF(M49>=0.22,"🟢 Отличен",IF(M49>=0.15,"🟡 За преглед","🔴 Нисък марж"))) | O49: Брошура 1 | P49: 1
A50: ОБЩО / СРЕДНО ЗА БЛАНКАТА: | I50: =IFERROR(AVERAGE(I15:I49),0) | L50: =IFERROR(AVERAGE(L15:L49),0) | M50: =IFERROR(AVERAGE(M15:M49),0) | P50: =SUM(P15:P49)

Sheet График_2027
A1: ОФИЦИАЛЕН ГРАФИК ЗА ПРОМОЦИОНАЛНИ БРОШУРИ — 2027 ГОДИНА
A2: Код на Брошурата | B2: Старт промоция (магазини) | C2: Край промоция (магазини) | D2: Период на промоцията | E2: Дни | F2: Период промо доставна цена (ЗКП, X-7) | G2: Краен срок за предложения | H2: Краен срок за предпечат (X-10) | I2: Старт ЗКП (ISO дата)
A3: Брошура № 01 | B3: 2027-01-09 | C3: 2027-01-17 | D3: 09.01.2027 – 17.01.2027 | E3: 9 | F3: 02.01.2027 – 17.01.2027 | G3: 28.12.2026 | H3: 30.12.2026 | I3: 2027-01-02
A4: Брошура № 02 | B4: 2027-01-23 | C4: 2027-01-31 | D4: 23.01.2027 – 31.01.2027 | E4: 9 | F4: 16.01.2027 – 31.01.2027 | G4: 11.01.2027 | H4: 13.01.2027 | I4: 2027-01-16
A5: Брошура № 03 | B5: 2027-02-06 | C5: 2027-02-14 | D5: 06.02.2027 – 14.02.2027 | E5: 9 | F5: 30.01.2027 – 14.02.2027 | G5: 25.01.2027 | H5: 27.01.2027 | I5: 2027-01-30
A6: Брошура № 04 | B6: 2027-02-20 | C6: 2027-02-28 | D6: 20.02.2027 – 28.02.2027 | E6: 9 | F6: 13.02.2027 – 28.02.2027 | G6: 08.02.2027 | H6: 10.02.2027 | I6: 2027-02-13
A7: Брошура № 05 | B7: 2027-03-06 | C7: 2027-03-14 | D7: 06.03.2027 – 14.03.2027 | E7: 9 | F7: 27.02.2027 – 14.03.2027 | G7: 22.02.2027 | H7: 24.02.2027 | I7: 2027-02-27
A8: Брошура № 06 | B8: 2027-03-20 | C8: 2027-03-28 | D8: 20.03.2027 – 28.03.2027 | E8: 9 | F8: 13.03.2027 – 28.03.2027 | G8: 08.03.2027 | H8: 10.03.2027 | I8: 2027-03-13
A9: Брошура № 07 | B9: 2027-04-03 | C9: 2027-04-11 | D9: 03.04.2027 – 11.04.2027 | E9: 9 | F9: 27.03.2027 – 11.04.2027 | G9: 22.03.2027 | H9: 24.03.2027 | I9: 2027-03-27
A10: Брошура № 08 | B10: 2027-04-17 | C10: 2027-04-25 | D10: 17.04.2027 – 25.04.2027 | E10: 9 | F10: 10.04.2027 – 25.04.2027 | G10: 05.04.2027 | H10: 07.04.2027 | I10: 2027-04-10
A11: Брошура № 09 | B11: 2027-04-29 | C11: 2027-05-09 | D11: 29.04.2027 – 09.05.2027 | E11: 11 | F11: 22.04.2027 – 09.05.2027 | G11: 17.04.2027 | H11: 19.04.2027 | I11: 2027-04-22
A12: Брошура № 10 | B12: 2027-05-22 | C12: 2027-05-30 | D12: 22.05.2027 – 30.05.2027 | E12: 9 | F12: 15.05.2027 – 30.05.2027 | G12: 10.05.2027 | H12: 12.05.2027 | I12: 2027-05-15
A13: Брошура № 11 | B13: 2027-06-05 | C13: 2027-06-13 | D13: 05.06.2027 – 13.06.2027 | E13: 9 | F13: 29.05.2027 – 13.06.2027 | G13: 24.05.2027 | H13: 26.05.2027 | I13: 2027-05-29
A14: Брошура № 12 | B14: 2027-06-19 | C14: 2027-06-27 | D14: 19.06.2027 – 27.06.2027 | E14: 9 | F14: 12.06.2027 – 27.06.2027 | G14: 07.06.2027 | H14: 09.06.2027 | I14: 2027-06-12
... A27: Брошура № 25 | B27: 2027-12-27 | C27: 2028-01-02 | D27: 27.12.2027 – 02.01.2028 | E27: 7 | F27: 20.12.2027 – 02.01.2028 | G27: 15.12.2027 | H27: 17.12.2027 | I27: 2027-12-20

Sheet Инструкции_и_ДТУ
A1: УКАЗАНИЯ ЗА УЧАСТИЕ В ПРОМОЦИОНАЛНИ БРОШУРИ — ВЕРИГА „БАКАЛИЯ“
A3: 1. Период на намалената доставна цена (ЗКП - Златно правило)
A4: • Промоционалната доставна цена (ЗКП) ЗАДЪЛЖИТЕЛНО влиза в сила точно 7 календарни дни преди старта на промоцията.
A5: • Пример: За брошура с период 09.01 - 17.01.2027 г., доставната промо цена важи от 02.01.2027 г. до 17.01.2027 г.
A6: • Цел: Осигуряване на навременно зареждане на Централния склад и 11-те супермаркета на промоционална себестойност.
A8: 2. Попълване и идентификация на артикулите
A9: • Моля попълвайте задължително Баркод (EAN-13) и/или Вашия код в Бакалия (Мистрал ID), за да се избегнат грешки при зареждането на касите.
A10: • Наименованието на артикула следва да бъде точно и ясно (вкл. грамаж / разфасовка), както следва да се изпише на етикета и карето.
A11: • При промоции тип „асортимент“ (различни видове/вкусове на една цена), посочете вкусовете в колона „Специфика / Забележка“.
A13: 3. Ценообразуване и целеви маржове
A14: • Предложената промоционална продажна цена (с ДДС) трябва да гарантира реално потребителско намаление и целевия брутен марж.
A15: • Колона „Статус на маржа“ изчислява автоматично доходността: 🟢 Отличен (над 22%), 🟡 За преглед (15-22%), 🔴 Нисък марж (под 15%).
... A26: • Запитвания и потвърждения се изпращат към търговския отдел на „Бакалия“: s.mart.tonev@gmail.com.

Sheet Експорт_Предпечат
A1: ТЕХНИЧЕСКИ ЕКСПОРТ КЪМ АГЕНЦИЯТА ЗА ПРЕДПЕЧАТ (100% СЪВМЕСТИМ ФОРМАТ)
A2: Арт. Номер | B2: Наименование артикул | C2: М. Ед | D2: Фирма | E2: Д.ц. | F2: Промо д.ц. | G2: Пр.ц. | H2: Промо пр.ц. | I2: Период | J2: Участия
A3: =IF(Бланка_Предложения!D15="","",IF(Бланка_Предложения!B15<>"",Бланка_Предложения!B15,Бланка_Предложения!C15)) | B3: =IF(Бланка_Предложения!D15="","",Бланка_Предложения!D15) | C3: =IF(Бланка_Предложения!D15="","",Бланка_Предложения!E15) | D3: =IF(Бланка_Предложения!D15="","",IF(Бланка_Предложения!F15<>"",Бланка_Предложения!F15,Бланка_Предложения!$D$9)) | E3: =IF(Бланка_Предложения!D15="","",Бланка_Предложения!G15) | F3: =IF(Бланка_Предложения!D15="","",Бланка_Предложения!H15) | G3: =IF(Бланка_Предложения!D15="","",Бланка_Предложения!J15) | H3: =IF(Бланка_Предложения!D15="","",Бланка_Предложения!K15) | I3: =IF(Бланка_Предложения!D15="","",Бланка_Предложения!O15) | J3: =IF(Бланка_Предложения!D15="","",Бланка_Предложения!P15)
A4: =IF(Бланка_Предложения!D16="","",IF(Бланка_Предложения!B16<>"",Бланка_Предложения!B16,Бланка_Предложения!C16)) | B4: =IF(Бланка_Предложения!D16="","",Бланка_Предложения!D16) | C4: =IF(Бланка_Предложения!D16="","",Бланка_Предложения!E16) | D4: =IF(Бланка_Предложения!D16="","",IF(Бланка_Предложения!F16<>"",Бланка_Предложения!F16,Бланка_Предложения!$D$9)) | E4: =IF(Бланка_Предложения!D16="","",Бланка_Предложения!G16) | F4: =IF(Бланка_Предложения!D16="","",Бланка_Предложения!H16) | G4: =IF(Бланка_Предложения!D16="","",Бланка_Предложения!J16) | H4: =IF(Бланка_Предложения!D16="","",Бланка_Предложения!K16) | I4: =IF(Бланка_Предложения!D16="","",Бланка_Предложения!O16) | J4: =IF(Бланка_Предложения!D16="","",Бланка_Предложения!P16)
A5: =IF(Бланка_Предложения!D17="","",IF(Бланка_Предложения!B17<>"",Бланка_Предложения!B17,Бланка_Предложения!C17)) | B5: =IF(Бланка_Предложения!D17="","",Бланка_Предложения!D17) | C5: =IF(Бланка_Предложения!D17="","",Бланка_Предложения!E17) | D5: =IF(Бланка_Предложения!D17="","",IF(Бланка_Предложения!F17<>"",Бланка_Предложения!F17,Бланка_Предложения!$D$9)) | E5: =IF(Бланка_Предложения!D17="","",Бланка_Предложения!G17) | F5: =IF(Бланка_Предложения!D17="","",Бланка_Предложения!H17) | G5: =IF(Бланка_Предложения!D17="","",Бланка_Предложения!J17) | H5: =IF(Бланка_Предложения!D17="","",Бланка_Предложения!K17) | I5: =IF(Бланка_Предложения!D17="","",Бланка_Предложения!O17) | J5: =IF(Бланка_Предложения!D17="","",Бланка_Предложения!P17)
A6: =IF(Бланка_Предложения!D18="","",IF(Бланка_Предложения!B18<>"",Бланка_Предложения!B18,Бланка_Предложения!C18)) | B6: =IF(Бланка_Предложения!D18="","",Бланка_Предложения!D18) | C6: =IF(Бланка_Предложения!D18="","",Бланка_Предложения!E18) | D6: =IF(Бланка_Предложения!D18="","",IF(Бланка_Предложения!F18<>"",Бланка_Предложения!F18,Бланка_Предложения!$D$9)) | E6: =IF(Бланка_Предложения!D18="","",Бланка_Предложения!G18) | F6: =IF(Бланка_Предложения!D18="","",Бланка_Предложения!H18) | G6: =IF(Бланка_Предложения!D18="","",Бланка_Предложения!J18) | H6: =IF(Бланка_Предложения!D18="","",Бланка_Предложения!K18) | I6: =IF(Бланка_Предложения!D18="","",Бланка_Предложения!O18) | J6: =IF(Бланка_Предложения!D18="","",Бланка_Предложения!P18)
A7: =IF(Бланка_Предложения!D19="","",IF(Бланка_Предложения!B19<>"",Бланка_Предложения!B19,Бланка_Предложения!C19)) | B7: =IF(Бланка_Предложения!D19="","",Бланка_Предложения!D19) | C7: =IF(Бланка_Предложения!D19="","",Бланка_Предложения!E19) | D7: =IF(Бланка_Предложения!D19="","",IF(Бланка_Предложения!F19<>"",Бланка_Предложения!F19,Бланка_Предложения!$D$9)) | E7: =IF(Бланка_Предложения!D19="","",Бланка_Предложения!G19) | F7: =IF(Бланка_Предложения!D19="","",Бланка_Предложения!H19) | G7: =IF(Бланка_Предложения!D19="","",Бланка_Предложения!J19) | H7: =IF(Бланка_Предложения!D19="","",Бланка_Предложения!K19) | I7: =IF(Бланка_Предложения!D19="","",Бланка_Предложения!O19) | J7: =IF(Бланка_Предложения!D19="","",Бланка_Предложения!P19)
A8: =IF(Бланка_Предложения!D20="","",IF(Бланка_Предложения!B20<>"",Бланка_Предложения!B20,Бланка_Предложения!C20)) | B8: =IF(Бланка_Предложения!D20="","",Бланка_Предложения!D20) | C8: =IF(Бланка_Предложения!D20="","",Бланка_Предложения!E20) | D8: =IF(Бланка_Предложения!D20="","",IF(Бланка_Предложения!F20<>"",Бланка_Предложения!F20,Бланка_Предложения!$D$9)) | E8: =IF(Бланка_Предложения!D20="","",Бланка_Предложения!G20) | F8: =IF(Бланка_Предложения!D20="","",Бланка_Предложения!H20) | G8: =IF(Бланка_Предложения!D20="","",Бланка_Предложения!J20) | H8: =IF(Бланка_Предложения!D20="","",Бланка_Предложения!K20) | I8: =IF(Бланка_Предложения!D20="","",Бланка_Предложения!O20) | J8: =IF(Бланка_Предложения!D20="","",Бланка_Предложения!P20)
A9: =IF(Бланка_Предложения!D21="","",IF(Бланка_Предложения!B21<>"",Бланка_Предложения!B21,Бланка_Предложения!C21)) | B9: =IF(Бланка_Предложения!D21="","",Бланка_Предложения!D21) | C9: =IF(Бланка_Предложения!D21="","",Бланка_Предложения!E21) | D9: =IF(Бланка_Предложения!D21="","",IF(Бланка_Предложения!F21<>"",Бланка_Предложения!F21,Бланка_Предложения!$D$9)) | E9: =IF(Бланка_Предложения!D21="","",Бланка_Предложения!G21) | F9: =IF(Бланка_Предложения!D21="","",Бланка_Предложения!H21) | G9: =IF(Бланка_Предложения!D21="","",Бланка_Предложения!J21) | H9: =IF(Бланка_Предложения!D21="","",Бланка_Предложения!K21) | I9: =IF(Бланка_Предложения!D21="","",Бланка_Предложения!O21) | J9: =IF(Бланка_Предложения!D21="","",Бланка_Предложения!P21)
A10: =IF(Бланка_Предложения!D22="","",IF(Бланка_Предложения!B22<>"",Бланка_Предложения!B22,Бланка_Предложения!C22)) | B10: =IF(Бланка_Предложения!D22="","",Бланка_Предложения!D22) | C10: =IF(Бланка_Предложения!D22="","",Бланка_Предложения!E22) | D10: =IF(Бланка_Предложения!D22="","",IF(Бланка_Предложения!F22<>"",Бланка_Предложения!F22,Бланка_Предложения!$D$9)) | E10: =IF(Бланка_Предложения!D22="","",Бланка_Предложения!G22) | F10: =IF(Бланка_Предложения!D22="","",Бланка_Предложения!H22) | G10: =IF(Бланка_Предложения!D22="","",Бланка_Предложения!J22) | H10: =IF(Бланка_Предложения!D22="","",Бланка_Предложения!K22) | I10: =IF(Бланка_Предложения!D22="","",Бланка_Предложения!O22) | J10: =IF(Бланка_Предложения!D22="","",Бланка_Предложения!P22)
A11: =IF(Бланка_Предложения!D23="","",IF(Бланка_Предложения!B23<>"",Бланка_Предложения!B23,Бланка_Предложения!C23)) | B11: =IF(Бланка_Предложения!D23="","",Бланка_Предложения!D23) | C11: =IF(Бланка_Предложения!D23="","",Бланка_Предложения!E23) | D11: =IF(Бланка_Предложения!D23="","",IF(Бланка_Предложения!F23<>"",Бланка_Предложения!F23,Бланка_Предложения!$D$9)) | E11: =IF(Бланка_Предложения!D23="","",Бланка_Предложения!G23) | F11: =IF(Бланка_Предложения!D23="","",Бланка_Предложения!H23) | G11: =IF(Бланка_Предложения!D23="","",Бланка_Предложения!J23) | H11: =IF(Бланка_Предложения!D23="","",Бланка_Предложения!K23) | I11: =IF(Бланка_Предложения!D23="","",Бланка_Предложения!O23) | J11: =IF(Бланка_Предложения!D23="","",Бланка_Предложения!P23)
A12: =IF(Бланка_Предложения!D24="","",IF(Бланка_Предложения!B24<>"",Бланка_Предложения!B24,Бланка_Предложения!C24)) | B12: =IF(Бланка_Предложения!D24="","",Бланка_Предложения!D24) | C12: =IF(Бланка_Предложения!D24="","",Бланка_Предложения!E24) | D12: =IF(Бланка_Предложения!D24="","",IF(Бланка_Предложения!F24<>"",Бланка_Предложения!F24,Бланка_Предложения!$D$9)) | E12: =IF(Бланка_Предложения!D24="","",Бланка_Предложения!G24) | F12: =IF(Бланка_Предложения!D24="","",Бланка_Предложения!H24) | G12: =IF(Бланка_Предложения!D24="","",Бланка_Предложения!J24) | H12: =IF(Бланка_Предложения!D24="","",Бланка_Предложения!K24) | I12: =IF(Бланка_Предложения!D24="","",Бланка_Предложения!O24) | J12: =IF(Бланка_Предложения!D24="","",Бланка_Предложения!P24)
A13: =IF(Бланка_Предложения!D25="","",IF(Бланка_Предложения!B25<>"",Бланка_Предложения!B25,Бланка_Предложения!C25)) | B13: =IF(Бланка_Предложения!D25="","",Бланка_Предложения!D25) | C13: =IF(Бланка_Предложения!D25="","",Бланка_Предложения!E25) | D13: =IF(Бланка_Предложения!D25="","",IF(Бланка_Предложения!F25<>"",Бланка_Предложения!F25,Бланка_Предложения!$D$9)) | E13: =IF(Бланка_Предложения!D25="","",Бланка_Предложения!G25) | F13: =IF(Бланка_Предложения!D25="","",Бланка_Предложения!H25) | G13: =IF(Бланка_Предложения!D25="","",Бланка_Предложения!J25) | H13: =IF(Бланка_Предложения!D25="","",Бланка_Предложения!K25) | I13: =IF(Бланка_Предложения!D25="","",Бланка_Предложения!O25) | J13: =IF(Бланка_Предложения!D25="","",Бланка_Предложения!P25)
A14: =IF(Бланка_Предложения!D26="","",IF(Бланка_Предложения!B26<>"",Бланка_Предложения!B26,Бланка_Предложения!C26)) | B14: =IF(Бланка_Предложения!D26="","",Бланка_Предложения!D26) | C14: =IF(Бланка_Предложения!D26="","",Бланка_Предложения!E26) | D14: =IF(Бланка_Предложения!D26="","",IF(Бланка_Предложения!F26<>"",Бланка_Предложения!F26,Бланка_Предложения!$D$9)) | E14: =IF(Бланка_Предложения!D26="","",Бланка_Предложения!G26) | F14: =IF(Бланка_Предложения!D26="","",Бланка_Предложения!H26) | G14: =IF(Бланка_Предложения!D26="","",Бланка_Предложения!J26) | H14: =IF(Бланка_Предложения!D26="","",Бланка_Предложения!K26) | I14: =IF(Бланка_Предложения!D26="","",Бланка_Предложения!O26) | J14: =IF(Бланка_Предложения!D26="","",Бланка_Предложения!P26)
... A37: =IF(Бланка_Предложения!D49="","",IF(Бланка_Предложения!B49<>"",Бланка_Предложения!B49,Бланка_Предложения!C49)) | B37: =IF(Бланка_Предложения!D49="","",Бланка_Предложения!D49) | C37: =IF(Бланка_Предложения!D49="","",Бланка_Предложения!E49) | D37: =IF(Бланка_Предложения!D49="","",IF(Бланка_Предложения!F49<>"",Бланка_Предложения!F49,Бланка_Предложения!$D$9)) | E37: =IF(Бланка_Предложения!D49="","",Бланка_Предложения!G49) | F37: =IF(Бланка_Предложения!D49="","",Бланка_Предложения!H49) | G37: =IF(Бланка_Предложения!D49="","",Бланка_Предложения!J49) | H37: =IF(Бланка_Предложения!D49="","",Бланка_Предложения!K49) | I37: =IF(Бланка_Предложения!D49="","",Бланка_Предложения!O49) | J37: =IF(Бланка_Предложения!D49="","",Бланка_Предложения!P49)

Sheet Експорт_Мистрал_ERP
A1: АВТОМАТИЗИРАН ЕКСПОРТ КЪМ МИСТРАЛ ERP (ПЦ ЗА КАСИ И ЗКП ЗА ДОСТАВКИ)
A2: ПРОМОЦИОНАЛНИ ПРОДАЖНИ ЦЕНИ (ПЦ) — КАСИ (11 МАГАЗИНА) | G2: ДОГОВОРЕНИ ПОКУПНИ ЦЕНИ (ЗКП) — ЦЕНТРАЛЕН СКЛАД И МАГАЗИНИ (СТАРТ X-7)
A3: Код на артикул | B3: Име на артикул | C3: Промо продажна цена | D3: Период от | E3: Период до | G3: Код на артикул | H3: Име на артикул | I3: Договорена покупна цена | J3: Период от | K3: Период до
A4: =IF(Бланка_Предложения!D15="","",Бланка_Предложения!B15) | B4: =IF(Бланка_Предложения!D15="","",Бланка_Предложения!D15) | C4: =IF(Бланка_Предложения!D15="","",Бланка_Предложения!K15) | D4: =IF(Бланка_Предложения!D15="","",VLOOKUP(Бланка_Предложения!$D$5, График_2027!$A$3:$I$27, 2, FALSE)) | E4: =IF(Бланка_Предложения!D15="","",VLOOKUP(Бланка_Предложения!$D$5, График_2027!$A$3:$I$27, 3, FALSE)) | G4: =IF(Бланка_Предложения!D15="","",Бланка_Предложения!B15) | H4: =IF(Бланка_Предложения!D15="","",Бланка_Предложения!D15) | I4: =IF(Бланка_Предложения!D15="","",Бланка_Предложения!H15) | J4: =IF(Бланка_Предложения!D15="","",VLOOKUP(Бланка_Предложения!$D$5, График_2027!$A$3:$I$27, 9, FALSE)) | K4: =IF(Бланка_Предложения!D15="","",VLOOKUP(Бланка_Предложения!$D$5, График_2027!$A$3:$I$27, 3, FALSE))
A5: =IF(Бланка_Предложения!D16="","",Бланка_Предложения!B16) | B5: =IF(Бланка_Предложения!D16="","",Бланка_Предложения!D16) | C5: =IF(Бланка_Предложения!D16="","",Бланка_Предложения!K16) | D5: =IF(Бланка_Предложения!D16="","",VLOOKUP(Бланка_Предложения!$D$5, График_2027!$A$3:$I$27, 2, FALSE)) | E5: =IF(Бланка_Предложения!D16="","",VLOOKUP(Бланка_Предложения!$D$5, График_2027!$A$3:$I$27, 3, FALSE)) | G5: =IF(Бланка_Предложения!D16="","",Бланка_Предложения!B16) | H5: =IF(Бланка_Предложения!D16="","",Бланка_Предложения!D16) | I5: =IF(Бланка_Предложения!D16="","",Бланка_Предложения!H16) | J5: =IF(Бланка_Предложения!D16="","",VLOOKUP(Бланка_Предложения!$D$5, График_2027!$A$3:$I$27, 9, FALSE)) | K5: =IF(Бланка_Предложения!D16="","",VLOOKUP(Бланка_Предложения!$D$5, График_2027!$A$3:$I$27, 3, FALSE))
A6: =IF(Бланка_Предложения!D17="","",Бланка_Предложения!B17) | B6: =IF(Бланка_Предложения!D17="","",Бланка_Предложения!D17) | C6: =IF(Бланка_Предложения!D17="","",Бланка_Предложения!K17) | D6: =IF(Бланка_Предложения!D17="","",VLOOKUP(Бланка_Предложения!$D$5, График_2027!$A$3:$I$27, 2, FALSE)) | E6: =IF(Бланка_Предложения!D17="","",VLOOKUP(Бланка_Предложения!$D$5, График_2027!$A$3:$I$27, 3, FALSE)) | G6: =IF(Бланка_Предложения!D17="","",Бланка_Предложения!B17) | H6: =IF(Бланка_Предложения!D17="","",Бланка_Предложения!D17) | I6: =IF(Бланка_Предложения!D17="","",Бланка_Предложения!H17) | J6: =IF(Бланка_Предложения!D17="","",VLOOKUP(Бланка_Предложения!$D$5, График_2027!$A$3:$I$27, 9, FALSE)) | K6: =IF(Бланка_Предложения!D17="","",VLOOKUP(Бланка_Предложения!$D$5, График_2027!$A$3:$I$27, 3, FALSE))
A7: =IF(Бланка_Предложения!D18="","",Бланка_Предложения!B18) | B7: =IF(Бланка_Предложения!D18="","",Бланка_Предложения!D18) | C7: =IF(Бланка_Предложения!D18="","",Бланка_Предложения!K18) | D7: =IF(Бланка_Предложения!D18="","",VLOOKUP(Бланка_Предложения!$D$5, График_2027!$A$3:$I$27, 2, FALSE)) | E7: =IF(Бланка_Предложения!D18="","",VLOOKUP(Бланка_Предложения!$D$5, График_2027!$A$3:$I$27, 3, FALSE)) | G7: =IF(Бланка_Предложения!D18="","",Бланка_Предложения!B18) | H7: =IF(Бланка_Предложения!D18="","",Бланка_Предложения!D18) | I7: =IF(Бланка_Предложения!D18="","",Бланка_Предложения!H18) | J7: =IF(Бланка_Предложения!D18="","",VLOOKUP(Бланка_Предложения!$D$5, График_2027!$A$3:$I$27, 9, FALSE)) | K7: =IF(Бланка_Предложения!D18="","",VLOOKUP(Бланка_Предложения!$D$5, График_2027!$A$3:$I$27, 3, FALSE))
A8: =IF(Бланка_Предложения!D19="","",Бланка_Предложения!B19) | B8: =IF(Бланка_Предложения!D19="","",Бланка_Предложения!D19) | C8: =IF(Бланка_Предложения!D19="","",Бланка_Предложения!K19) | D8: =IF(Бланка_Предложения!D19="","",VLOOKUP(Бланка_Предложения!$D$5, График_2027!$A$3:$I$27, 2, FALSE)) | E8: =IF(Бланка_Предложения!D19="","",VLOOKUP(Бланка_Предложения!$D$5, График_2027!$A$3:$I$27, 3, FALSE)) | G8: =IF(Бланка_Предложения!D19="","",Бланка_Предложения!B19) | H8: =IF(Бланка_Предложения!D19="","",Бланка_Предложения!D19) | I8: =IF(Бланка_Предложения!D19="","",Бланка_Предложения!H19) | J8: =IF(Бланка_Предложения!D19="","",VLOOKUP(Бланка_Предложения!$D$5, График_2027!$A$3:$I$27, 9, FALSE)) | K8: =IF(Бланка_Предложения!D19="","",VLOOKUP(Бланка_Предложения!$D$5, График_2027!$A$3:$I$27, 3, FALSE))
A9: =IF(Бланка_Предложения!D20="","",Бланка_Предложения!B20) | B9: =IF(Бланка_Предложения!D20="","",Бланка_Предложения!D20) | C9: =IF(Бланка_Предложения!D20="","",Бланка_Предложения!K20) | D9: =IF(Бланка_Предложения!D20="","",VLOOKUP(Бланка_Предложения!$D$5, График_2027!$A$3:$I$27, 2, FALSE)) | E9: =IF(Бланка_Предложения!D20="","",VLOOKUP(Бланка_Предложения!$D$5, График_2027!$A$3:$I$27, 3, FALSE)) | G9: =IF(Бланка_Предложения!D20="","",Бланка_Предложения!B20) | H9: =IF(Бланка_Предложения!D20="","",Бланка_Предложения!D20) | I9: =IF(Бланка_Предложения!D20="","",Бланка_Предложения!H20) | J9: =IF(Бланка_Предложения!D20="","",VLOOKUP(Бланка_Предложения!$D$5, График_2027!$A$3:$I$27, 9, FALSE)) | K9: =IF(Бланка_Предложения!D20="","",VLOOKUP(Бланка_Предложения!$D$5, График_2027!$A$3:$I$27, 3, FALSE))
A10: =IF(Бланка_Предложения!D21="","",Бланка_Предложения!B21) | B10: =IF(Бланка_Предложения!D21="","",Бланка_Предложения!D21) | C10: =IF(Бланка_Предложения!D21="","",Бланка_Предложения!K21) | D10: =IF(Бланка_Предложения!D21="","",VLOOKUP(Бланка_Предложения!$D$5, График_2027!$A$3:$I$27, 2, FALSE)) | E10: =IF(Бланка_Предложения!D21="","",VLOOKUP(Бланка_Предложения!$D$5, График_2027!$A$3:$I$27, 3, FALSE)) | G10: =IF(Бланка_Предложения!D21="","",Бланка_Предложения!B21) | H10: =IF(Бланка_Предложения!D21="","",Бланка_Предложения!D21) | I10: =IF(Бланка_Предложения!D21="","",Бланка_Предложения!H21) | J10: =IF(Бланка_Предложения!D21="","",VLOOKUP(Бланка_Предложения!$D$5, График_2027!$A$3:$I$27, 9, FALSE)) | K10: =IF(Бланка_Предложения!D21="","",VLOOKUP(Бланка_Предложения!$D$5, График_2027!$A$3:$I$27, 3, FALSE))
A11: =IF(Бланка_Предложения!D22="","",Бланка_Предложения!B22) | B11: =IF(Бланка_Предложения!D22="","",Бланка_Предложения!D22) | C11: =IF(Бланка_Предложения!D22="","",Бланка_Предложения!K22) | D11: =IF(Бланка_Предложения!D22="","",VLOOKUP(Бланка_Предложения!$D$5, График_2027!$A$3:$I$27, 2, FALSE)) | E11: =IF(Бланка_Предложения!D22="","",VLOOKUP(Бланка_Предложения!$D$5, График_2027!$A$3:$I$27, 3, FALSE)) | G11: =IF(Бланка_Предложения!D22="","",Бланка_Предложения!B22) | H11: =IF(Бланка_Предложения!D22="","",Бланка_Предложения!D22) | I11: =IF(Бланка_Предложения!D22="","",Бланка_Предложения!H22) | J11: =IF(Бланка_Предложения!D22="","",VLOOKUP(Бланка_Предложения!$D$5, График_2027!$A$3:$I$27, 9, FALSE)) | K11: =IF(Бланка_Предложения!D22="","",VLOOKUP(Бланка_Предложения!$D$5, График_2027!$A$3:$I$27, 3, FALSE))
A12: =IF(Бланка_Предложения!D23="","",Бланка_Предложения!B23) | B12: =IF(Бланка_Предложения!D23="","",Бланка_Предложения!D23) | C12: =IF(Бланка_Предложения!D23="","",Бланка_Предложения!K23) | D12: =IF(Бланка_Предложения!D23="","",VLOOKUP(Бланка_Предложения!$D$5, График_2027!$A$3:$I$27, 2, FALSE)) | E12: =IF(Бланка_Предложения!D23="","",VLOOKUP(Бланка_Предложения!$D$5, График_2027!$A$3:$I$27, 3, FALSE)) | G12: =IF(Бланка_Предложения!D23="","",Бланка_Предложения!B23) | H12: =IF(Бланка_Предложения!D23="","",Бланка_Предложения!D23) | I12: =IF(Бланка_Предложения!D23="","",Бланка_Предложения!H23) | J12: =IF(Бланка_Предложения!D23="","",VLOOKUP(Бланка_Предложения!$D$5, График_2027!$A$3:$I$27, 9, FALSE)) | K12: =IF(Бланка_Предложения!D23="","",VLOOKUP(Бланка_Предложения!$D$5, График_2027!$A$3:$I$27, 3, FALSE))
A13: =IF(Бланка_Предложения!D24="","",Бланка_Предложения!B24) | B13: =IF(Бланка_Предложения!D24="","",Бланка_Предложения!D24) | C13: =IF(Бланка_Предложения!D24="","",Бланка_Предложения!K24) | D13: =IF(Бланка_Предложения!D24="","",VLOOKUP(Бланка_Предложения!$D$5, График_2027!$A$3:$I$27, 2, FALSE)) | E13: =IF(Бланка_Предложения!D24="","",VLOOKUP(Бланка_Предложения!$D$5, График_2027!$A$3:$I$27, 3, FALSE)) | G13: =IF(Бланка_Предложения!D24="","",Бланка_Предложения!B24) | H13: =IF(Бланка_Предложения!D24="","",Бланка_Предложения!D24) | I13: =IF(Бланка_Предложения!D24="","",Бланка_Предложения!H24) | J13: =IF(Бланка_Предложения!D24="","",VLOOKUP(Бланка_Предложения!$D$5, График_2027!$A$3:$I$27, 9, FALSE)) | K13: =IF(Бланка_Предложения!D24="","",VLOOKUP(Бланка_Предложения!$D$5, График_2027!$A$3:$I$27, 3, FALSE))
A14: =IF(Бланка_Предложения!D25="","",Бланка_Предложения!B25) | B14: =IF(Бланка_Предложения!D25="","",Бланка_Предложения!D25) | C14: =IF(Бланка_Предложения!D25="","",Бланка_Предложения!K25) | D14: =IF(Бланка_Предложения!D25="","",VLOOKUP(Бланка_Предложения!$D$5, График_2027!$A$3:$I$27, 2, FALSE)) | E14: =IF(Бланка_Предложения!D25="","",VLOOKUP(Бланка_Предложения!$D$5, График_2027!$A$3:$I$27, 3, FALSE)) | G14: =IF(Бланка_Предложения!D25="","",Бланка_Предложения!B25) | H14: =IF(Бланка_Предложения!D25="","",Бланка_Предложения!D25) | I14: =IF(Бланка_Предложения!D25="","",Бланка_Предложения!H25) | J14: =IF(Бланка_Предложения!D25="","",VLOOKUP(Бланка_Предложения!$D$5, График_2027!$A$3:$I$27, 9, FALSE)) | K14: =IF(Бланка_Предложения!D25="","",VLOOKUP(Бланка_Предложения!$D$5, График_2027!$A$3:$I$27, 3, FALSE))
A15: =IF(Бланка_Предложения!D26="","",Бланка_Предложения!B26) | B15: =IF(Бланка_Предложения!D26="","",Бланка_Предложения!D26) | C15: =IF(Бланка_Предложения!D26="","",Бланка_Предложения!K26) | D15: =IF(Бланка_Предложения!D26="","",VLOOKUP(Бланка_Предложения!$D$5, График_2027!$A$3:$I$27, 2, FALSE)) | E15: =IF(Бланка_Предложения!D26="","",VLOOKUP(Бланка_Предложения!$D$5, График_2027!$A$3:$I$27, 3, FALSE)) | G15: =IF(Бланка_Предложения!D26="","",Бланка_Предложения!B26) | H15: =IF(Бланка_Предложения!D26="","",Бланка_Предложения!D26) | I15: =IF(Бланка_Предложения!D26="","",Бланка_Предложения!H26) | J15: =IF(Бланка_Предложения!D26="","",VLOOKUP(Бланка_Предложения!$D$5, График_2027!$A$3:$I$27, 9, FALSE)) | K15: =IF(Бланка_Предложения!D26="","",VLOOKUP(Бланка_Предложения!$D$5, График_2027!$A$3:$I$27, 3, FALSE))
... A38: =IF(Бланка_Предложения!D49="","",Бланка_Предложения!B49) | B38: =IF(Бланка_Предложения!D49="","",Бланка_Предложения!D49) | C38: =IF(Бланка_Предложения!D49="","",Бланка_Предложения!K49) | D38: =IF(Бланка_Предложения!D49="","",VLOOKUP(Бланка_Предложения!$D$5, График_2027!$A$3:$I$27, 2, FALSE)) | E38: =IF(Бланка_Предложения!D49="","",VLOOKUP(Бланка_Предложения!$D$5, График_2027!$A$3:$I$27, 3, FALSE)) | G38: =IF(Бланка_Предложения!D49="","",Бланка_Предложения!B49) | H38: =IF(Бланка_Предложения!D49="","",Бланка_Предложения!D49) | I38: =IF(Бланка_Предложения!D49="","",Бланка_Предложения!H49) | J38: =IF(Бланка_Предложения!D49="","",VLOOKUP(Бланка_Предложения!$D$5, График_2027!$A$3:$I$27, 9, FALSE)) | K38: =IF(Бланка_Предложения!D49="","",VLOOKUP(Бланка_Предложения!$D$5, График_2027!$A$3:$I$27, 3, FALSE))
